gitlabcli
